lybluely/__init__.py
lybluely/lybluely.py
lybluely-5.0.3.dist-info/LICENSE
lybluely-5.0.3.dist-info/METADATA
lybluely-5.0.3.dist-info/WHEEL
lybluely-5.0.3.dist-info/top_level.txt
lybluely-5.0.3.dist-info/RECORD
