Metadata-Version: 2.1
Name: lybluely
Version: 5.0.3
Summary: This is a test
Home-page: https://upload.pypi.org/legacy
Author: lybule52
Author-email: ly352hz@163.com
License: UNKNOWN
Platform: UNKNOWN
Classifier: Programming Language :: Python :: 3
License-File: LICENSE
